{
  "canonical": "https://smarthernews.com/coffee-talk-3/",
  "ogUrl": "https://smarthernews.com/coffee-talk-3/",
  "ogTitle": "coffee talk - smarther news",
  "ogDescription": "",
  "ogImage": "https://smarthernews.com/wp-content/uploads/2018/08/share-placeholder-v2.png",
  "datePublished": "2018-11-30T03:01:16+00:00",
  "dateModified": "2018-12-01T03:03:14+00:00",
  "articleSection": "coffee talk",
  "contentType": "quickreads",
  "category": "coffee talk",
  "colorClass": "light-yellow",
  "background_image": "https://smarthernews.com/wp-content/uploads/2018/02/home-office-06-1-360x360.jpg",
  "card_1": {
    "cardText": "November 29, 2018\n\n[Watch Now](https://www.youtube.com/embed/2Pizy486uzE?enablejsapi=1&autoplay=1&rel=0)",
    "card_citation": "Watch Now"
  },
  "card_10": {
    "cardText": "[view sources](https://smarthernews.com/coffee-talk-3/)"
  },
  "body": "  <p></p><div class=\"iframe-container\"><iframe title=\"SmartHER News-Coffee Talk-11/29/18\" src=\"https://www.youtube.com/embed/2Pizy486uzE?feature=oembed\" allow=\"accelerometer; autoplay; encrypted-media; gyroscope; picture-in-picture\" allowfullscreen=\"\" frameborder=\"0\" height=\"360\" width=\"640\"></iframe><div>{{&lt; youtube 2Pizy486uzE &gt;}}</div><div>{{&lt; youtube 2Pizy486uzE &gt;}}</div></div><p></p> "
}