{
  "canonical": "https://smarthernews.com/coffee-talk-2/",
  "ogUrl": "https://smarthernews.com/coffee-talk-2/",
  "ogTitle": "coffee talk - smarther news",
  "ogDescription": "",
  "ogImage": "https://smarthernews.com/wp-content/uploads/2018/08/share-placeholder-v2.png",
  "datePublished": "2018-11-30T13:55:52+00:00",
  "dateModified": "2018-12-01T02:57:51+00:00",
  "articleSection": "coffee talk",
  "contentType": "quickreads",
  "category": "coffee talk",
  "colorClass": "light-pink",
  "background_image": "https://smarthernews.com/wp-content/uploads/2018/09/shn_desk-min-1.png",
  "card_1": {
    "cardText": "November 30, 2018\n\n[Watch Now](https://www.youtube.com/embed/8AEL1J1WMoI?enablejsapi=1&autoplay=1&rel=0)",
    "card_citation": "Watch Now"
  },
  "card_10": {
    "cardText": "[view sources](https://smarthernews.com/coffee-talk-2/)"
  },
  "body": "  <p></p><div class=\"iframe-container\"><iframe title=\"SmarHER News-Coffee Talk-11/30/18\" src=\"https://www.youtube.com/embed/8AEL1J1WMoI?feature=oembed\" allow=\"accelerometer; autoplay; encrypted-media; gyroscope; picture-in-picture\" allowfullscreen=\"\" frameborder=\"0\" height=\"360\" width=\"640\"></iframe><div>{{&lt; youtube 8AEL1J1WMoI &gt;}}</div><div>{{&lt; youtube 8AEL1J1WMoI &gt;}}</div></div><p></p> "
}